authentication_app/__init__.py
authentication_app/admin.py
authentication_app/apps.py
authentication_app/demo.py
authentication_app/models.py
authentication_app/tests.py
authentication_app/urls.py
authentication_app/views.py
authentication_app/JWT/__init__.py
authentication_app/JWT/core.py
authentication_app/JWT/exceptions.py
authentication_app/migrations/__init__.py
authentication_app/utils/__init__.py
authentication_app/utils/redis_helper.py
authentication_app/utils/response_handler.py
authentication_app/utils/userConfig.py
Sergei_JWT-0.4.dist-info/METADATA
Sergei_JWT-0.4.dist-info/WHEEL
Sergei_JWT-0.4.dist-info/top_level.txt
Sergei_JWT-0.4.dist-info/RECORD
